{
    "RESULT": {
        "OIL": [
            {
                "TRADE_DT": "20230113",
                "PRODCD": "B034",
                "PRODNM": "고급휘발유",
                "PRICE": "1854.23",
                "DIFF": "-3.13"
            },
            {
                "TRADE_DT": "20230113",
                "PRODCD": "D047",
                "PRODNM": "자동차용경유",
                "PRICE": "1674.32",
                "DIFF": "-4.90"
            },
            {
                "TRADE_DT": "20230113",
                "PRODCD": "B027",
                "PRODNM": "휘발유",
                "PRICE": "1559.72",
                "DIFF": "-0.51"
            },
            {
                "TRADE_DT": "20230113",
                "PRODCD": "C004",
                "PRODNM": "실내등유",
                "PRICE": "1497.01",
                "DIFF": "-2.10"
            },
            {
                "TRADE_DT": "20230113",
                "PRODCD": "K015",
                "PRODNM": "자동차용부탄",
                "PRICE": "1019.48",
                "DIFF": "+0.06"
            }
        ]
    }
}